pinax/__init__.py
pinax/news/__init__.py
pinax/news/admin.py
pinax/news/apps.py
pinax/news/models.py
pinax/news/specs.py
pinax/news/utils.py
pinax/news/migrations/0001_initial.py
pinax/news/migrations/0002_news_press_release.py
pinax/news/migrations/0003_auto_20160905_1114.py
pinax/news/migrations/__init__.py
pinax/news/templatetags/__init__.py
pinax/news/templatetags/pinax_news_tags.py
pinax/news/tests/__init__.py
pinax/news/tests/tests.py
pinax_news-3.0.0.dist-info/AUTHORS
pinax_news-3.0.0.dist-info/LICENSE
pinax_news-3.0.0.dist-info/METADATA
pinax_news-3.0.0.dist-info/WHEEL
pinax_news-3.0.0.dist-info/top_level.txt
pinax_news-3.0.0.dist-info/RECORD
